{
  "character_name": "パソ館たん/パソコン館たん",
  "screen_name": "bicpkanhonten",
  "fetched_at": "2025-12-20T10:23:15.415Z",
  "tweets": [
    {
      "id": "2002302964908933329",
      "text": "／\nフルサイズデビュー応援📣\n α7 V登場の今、中古市場がアツい🔥\n＼\n\n✅憧れの名機が身近に \n✅軽量・人気モデルも充実 \n✅買替需要で良品が続々入荷！\n\n運命の1台がきっと見つかる✨\n専門スタッフが最適なセットも提案します！\nぜひ当店自慢の2階中古カメラコーナーへお越しください！☺️ https://t.co/BEUjPyQtuq",
      "createdAt": "Sat Dec 20 09:00:02 +0000 2025",
      "authorName": "ビックカメラ 池袋 カメラ・パソコン館📷💻",
      "authorScreenName": "bicpkanhonten",
      "mediaUrls": [
        "https://pbs.twimg.com/media/G8mOCNFbMAEPFpj.png"
      ]
    },
    {
      "id": "2002295407372853269",
      "text": "🎉【SoftBank／Y!mobile 大感謝祭】🎉\n12/29までの期間限定！\n富士通製PCのご購入と同時に\nSoftBank 光 または SoftBank Air を新規ご契約いただくと…\n👉 最大62,000円分お得に！\n年末だけのお得なチャンスです✨\n📍ぜひ当店 5階までお越しくださいませ！ https://t.co/DhoYMediRV",
      "createdAt": "Sat Dec 20 08:30:00 +0000 2025",
      "authorName": "ビックカメラ 池袋 カメラ・パソコン館📷💻",
      "authorScreenName": "bicpkanhonten",
      "mediaUrls": [
        "https://pbs.twimg.com/media/G8mRLg3bMAMDI93.jpg"
      ]
    },
    {
      "id": "2002287189028442224",
      "text": "＼緊急入荷！／\n\nCORSAIR　XENEON EDGE 14.5インチ\nLCDタッチスクリーンが緊急入荷しました！\n\n✅システム情報\n✅Discordチャット\n✅Youtube画面 ……\nなど、様々な使い方ができます！✨\n\nコンパクトサイズのサブタッチスクリーンをお探しの方！ぜひ当店6階までお越し下さい！ https://t.co/58iyPydrBv",
      "createdAt": "Sat Dec 20 07:57:21 +0000 2025",
      "authorName": "ビックカメラ 池袋 カメラ・パソコン館📷💻",
      "authorScreenName": "bicpkanhonten",
      "mediaUrls": [
        "https://pbs.twimg.com/media/G8mMBwQbMAIVM-8.jpg",
        "https://pbs.twimg.com/media/G8mNgNKa8AAK6OO.png"
      ]
    },
    {
      "id": "2002284999698010553",
      "text": "🎁プレゼントにおすすめ🎁\n離れた場所に住んでいても写真を送れる、\nwifi付デジタルフォトフレーム！\n\nタッチパネルで操作簡単！\nスマホより大きく写真が見られ贈り物に大人気です✨\n\n販売員おすすめはKodak RCF-1018W！\n木製フレームがインテリアに馴染みます💞\nB1Fにて展示中です☺ https://t.co/OsAKrtjezC",
      "createdAt": "Sat Dec 20 07:48:39 +0000 2025",
      "authorName": "ビックカメラ 池袋 カメラ・パソコン館📷💻",
      "authorScreenName": "bicpkanhonten",
      "mediaUrls": [
        "https://pbs.twimg.com/media/G8mK7u6bUAAe5wl.png",
        "https://pbs.twimg.com/media/G8mK_hBaEAAcP-j.jpg"
      ]
    },
    {
      "id": "2002245312271052855",
      "text": "／\nEPSONプリンター購入イベント開催中🌟\n＼\n\n20日・21日の2日間限定❣️\n当店でEPSONプリンターを購入していただくと、\nチームラボペアチケットなどが当たる抽選会に参加できます🌈\n\nさらに対象機種購入でEPSONキャッシュバックキャンペーンもある今がチャンス☺️✨\n\n3階でお待ちしております‼️ https://t.co/QZe2wLxZsg",
      "createdAt": "Sat Dec 20 05:10:57 +0000 2025",
      "authorName": "ビックカメラ 池袋 カメラ・パソコン館📷💻",
      "authorScreenName": "bicpkanhonten",
      "mediaUrls": [
        "https://pbs.twimg.com/media/G8lnUXRbkAAb9-8.jpg"
      ]
    },
    {
      "id": "2002214962916393164",
      "text": "\\ルーター買い替えなら今がチャンス！/\n\n只今ビックカメラではルーター下取りキャンペーンを実施中。\n本日から新しく2モデルが下取りキャンペーンに追加されました！\n\n下取りを利用すれば、最新のWi-Fi 7対応モデルへ賢くシフトできますので当店4階までお越しくださいませ！ https://t.co/JF9Iw7b2v6",
      "createdAt": "Sat Dec 20 03:10:21 +0000 2025",
      "authorName": "ビックカメラ 池袋 カメラ・パソコン館📷💻",
      "authorScreenName": "bicpkanhonten",
      "mediaUrls": [
        "https://pbs.twimg.com/media/G8lLSN5bMAEEQc_.jpg",
        "https://pbs.twimg.com/media/G8lLa7ybAAATmbe.png",
        "https://pbs.twimg.com/media/G8lLdeKaEAAvTr0.jpg"
      ]
    },
    {
      "id": "2002197264064987401",
      "text": "🎄FUJIFILM X half チェキ体験会開催中❢  \n\n🗓️12/19(金)・20(土)・21(日) \n🕚11:00～🕖19:00  \n\nX half での撮影とinstax Linkでのプリント体験会開催します。 \nご購入者様には数量限定クリスマスプレゼントもご用意しております🎁\n\nお友達や恋人へのプレゼントとしても人気です📷\n#チェキ #Xhalf https://t.co/1syPxvnMgS",
      "createdAt": "Sat Dec 20 02:00:01 +0000 2025",
      "authorName": "ビックカメラ 池袋 カメラ・パソコン館📷💻",
      "authorScreenName": "bicpkanhonten",
      "mediaUrls": [
        "https://pbs.twimg.com/media/G8hdZtobgAAJBVx.jpg"
      ]
    },
    {
      "id": "2002197261028061492",
      "text": "＼ASUS Winter Campaign／\n🗓️12/20(土)・21(日)\n🕚11:00〜🕗20:00\n\nキャンペーン期間中、ASUS専門販売員がゲーミングPC購入のお手伝いをさせて頂きます！\n\n対象ゲーミングPCご購入者様へは、\nイヤホン・ヘッドセット等の素敵な🎄クリスマスプレゼントもご用意してます。\n\n当店６階でお待ちしています🎅 https://t.co/ToLAdiZbSZ",
      "createdAt": "Sat Dec 20 02:00:00 +0000 2025",
      "authorName": "ビックカメラ 池袋 カメラ・パソコン館📷💻",
      "authorScreenName": "bicpkanhonten",
      "mediaUrls": [
        "https://pbs.twimg.com/media/G8h6KfYbAAAATmD.jpg",
        "https://pbs.twimg.com/media/G8h6zl2bgAAoXyl.jpg"
      ]
    },
    {
      "id": "2002189710253519109",
      "text": "＼ASUS Winter Campaign／\n\n12/20(土)～28(日)の期間にASUS製品ご購入で、\nオリジナルグッズをプレゼント！\nROG/TUF Gaming・ROGAllyシリーズ全機種が対象！\n\nお勧めはRTX5060搭載『TUF Gaming F16!』\n高性能でゲームがサクサク快適！\n\n是非この機会をお見逃しなく！ https://t.co/7TlDKCYm1M",
      "createdAt": "Sat Dec 20 01:30:00 +0000 2025",
      "authorName": "ビックカメラ 池袋 カメラ・パソコン館📷💻",
      "authorScreenName": "bicpkanhonten",
      "mediaUrls": [
        "https://pbs.twimg.com/media/G8h_M42bEAAcaFb.jpg",
        "https://pbs.twimg.com/media/G8h_M5GagAAnvqb.jpg"
      ]
    },
    {
      "id": "2002182294979899838",
      "text": "／\nNintendo #Switch2 緊急入荷‼️\n＼\n\nご購入条件は以下の画像をご確認ください。\n多くのお客様にお求めいただける様に、Ａ・Ｂいずれかと①～⑤の全てを満たす販売条件を定めさせて頂いています☺️\n\nご購入希望のお客様は当店7階レジカウンターへお越し下さい🏃‍♀️💨\n\n※数量限定の為、無くなり次第終了 https://t.co/BfCLun0SKG",
      "createdAt": "Sat Dec 20 01:00:32 +0000 2025",
      "authorName": "ビックカメラ 池袋 カメラ・パソコン館📷💻",
      "authorScreenName": "bicpkanhonten",
      "mediaUrls": [
        "https://pbs.twimg.com/media/G8h-CsAaAAAoksR.png",
        "https://pbs.twimg.com/media/G8h-DhgaUAAYxv2.png"
      ]
    },
    {
      "id": "2001895276689449032",
      "text": "＼学生🏫新社会人🔰にオススメ／\n\n✨数量限定✨\nSurface新生活応援モデルが本日発売‼️\n\nSurface ProとLaptopから選べます。\n今年は学生の方だけでなく、25歳以下の方が対象で、\n人気のSurfaceをオトクに手に入れるチャンスです😝\n\n当店5階パソコンコーナーで自分に合った1台を選んでみて下さい✨ https://t.co/K9lo1XkSED",
      "createdAt": "Fri Dec 19 06:00:02 +0000 2025",
      "authorName": "ビックカメラ 池袋 カメラ・パソコン館📷💻",
      "authorScreenName": "bicpkanhonten",
      "mediaUrls": [
        "https://pbs.twimg.com/media/G8glsITbcAAb_tg.jpg",
        "https://pbs.twimg.com/media/G8gltr5b0AABJWs.jpg",
        "https://pbs.twimg.com/media/G8glvj8asAEl7tZ.png",
        "https://pbs.twimg.com/media/G8glwbPakAMM6oZ.jpg"
      ]
    },
    {
      "id": "2001854114838524038",
      "text": "🐎まだ間に合います！年内仕上げ🌅\n\nB1Fにて #年賀状 のご注文を承り中🎍\n店内印刷仕上げなら、なんと最短1時間でお渡しできちゃいます✨\n高画質印画紙仕上げもまだまだ年内仕上げ間に合います！\n写真入りもイラストタイプもデザインはよりどりみどり💞\nお気軽にB1Fまでお問い合わせくださいませ〜🎶 https://t.co/Hqm7w7BTOh",
      "createdAt": "Fri Dec 19 03:16:28 +0000 2025",
      "authorName": "ビックカメラ 池袋 カメラ・パソコン館📷💻",
      "authorScreenName": "bicpkanhonten",
      "mediaUrls": [
        "https://pbs.twimg.com/media/G8gDlShaUAAN8pU.jpg",
        "https://pbs.twimg.com/media/G8gDoPOacAAbJpO.jpg"
      ]
    },
    {
      "id": "2001819778194010523",
      "text": "／\nいよいよ本日発売‼️\n＼\n話題のソニー新製品\"α7V\"が発売しました🎉\n\nAIを活用したAF、プリキャプチャー機能、4軸マルチアングル液晶など新機能が盛りだくさん☺️\nお試しできる展示機もご用意しました💪\n\nぜひ当店2階カメラコーナーへお越し下さい🏃💨 https://t.co/DTVfyf1Bjw",
      "createdAt": "Fri Dec 19 01:00:01 +0000 2025",
      "authorName": "ビックカメラ 池袋 カメラ・パソコン館📷💻",
      "authorScreenName": "bicpkanhonten",
      "mediaUrls": [
        "https://pbs.twimg.com/media/G8dIe37aYAEP13K.jpg"
      ]
    }
  ]
}